mmeson/__init__.py
mmeson/__main__.py
mmeson/cli.py
mmeson/meson_interface.py
mmeson/options.py
mmeson/singleton.py
mmeson/tui.py
mmeson-0.2.0.dist-info/LICENSE.txt
mmeson-0.2.0.dist-info/METADATA
mmeson-0.2.0.dist-info/WHEEL
mmeson-0.2.0.dist-info/entry_points.txt
mmeson-0.2.0.dist-info/top_level.txt
mmeson-0.2.0.dist-info/RECORD
