Metadata-Version: 2.1
Name: mmeson
Version: 0.2.0
Summary: ccmake for Meson projects
License: EUROPEAN UNION PUBLIC LICENCE v. 1.2
Project-URL: Documentation, https://stephanlachnit.github.io/mmeson/
Project-URL: Source, https://github.com/stephanlachnit/mmeson
Project-URL: Bug Tracker, https://github.com/stephanlachnit/mmeson/issues
Keywords: meson,ccmake
Classifier: Topic :: Software Development :: Build Tools
Classifier: License :: OSI Approved
Classifier: License :: OSI Approved :: European Union Public Licence 1.2 (EUPL 1.2)
Classifier: Programming Language :: Python :: 3
Classifier: Programming Language :: Python :: 3.9
Classifier: Programming Language :: Python :: 3.10
Classifier: Programming Language :: Python :: 3.11
Classifier: Development Status :: 3 - Alpha
Requires-Python: >=3.9
License-File: LICENSE.txt
Requires-Dist: urwid
Requires-Dist: setuptools
Provides-Extra: docs
Requires-Dist: sphinx ; extra == 'docs'
Requires-Dist: sphinx-rtd-theme ; extra == 'docs'
Requires-Dist: myst-parser ; extra == 'docs'
Requires-Dist: sphinxcontrib.apidoc ; extra == 'docs'
Requires-Dist: sphinx-paramlinks ; extra == 'docs'
Provides-Extra: test
Requires-Dist: pytest ; extra == 'test'
